pyseq_core/__init__.py
pyseq_core/base_com.py
pyseq_core/base_instruments.py
pyseq_core/base_protocol.py
pyseq_core/base_reagents.py
pyseq_core/base_system.py
pyseq_core/reservation_system.py
pyseq_core/resources/default.toml
pyseq_core/resources/machine_settings.yaml
pyseq_core/resources/test_experiment.toml
pyseq_core/resources/test_protocol.yaml
pyseq_core/resources/test_roi.toml
pyseq_core/roi_manager.py
pyseq_core/utils.py
pyseq_core-1.1.0a0.dist-info/WHEEL
pyseq_core-1.1.0a0.dist-info/METADATA
pyseq_core-1.1.0a0.dist-info/RECORD
