Metadata-Version: 2.3
Name: pyseq-core
Version: 1.1.0a0
Summary: Core Package for Open Source Control Software to Control Sequencers.
Author: Kunal Pandit
Author-email: Kunal Pandit <kpandit@nygenome.org>
Classifier: Programming Language :: Python :: 3
Classifier: License :: OSI Approved :: MIT License
Requires-Dist: pydantic>=2.11.7
Requires-Dist: tomlkit>=0.13.3
Requires-Dist: attrs>=25.3.0
Requires-Dist: pyyaml>=6.0.2
Requires-Dist: pyserial>=3.5
Requires-Python: >=3.11
Project-URL: Homepage, https://github.com/pypa/sampleproject
Project-URL: Issues, https://github.com/pypa/sampleproject/issues
Provides-Extra: dev
